CHANGES.txt
LICENSE.txt
MANIFEST.in
setup.cfg
setup.py
django_yaml_redirects/__init__.py
django_yaml_redirects.egg-info/PKG-INFO
django_yaml_redirects.egg-info/SOURCES.txt
django_yaml_redirects.egg-info/dependency_links.txt
django_yaml_redirects.egg-info/requires.txt
django_yaml_redirects.egg-info/top_level.txt