Metadata-Version: 1.0
Name: django-yaml-redirects
Version: 0.5.4
Summary: A simple redirects utility that uses a YAML file for redirects definitions
Home-page: https://github.com/ubuntudesign/django-yaml-redirects
Author: Canonical Webteam
Author-email: UNKNOWN
License: UNKNOWN
Platform: UNKNOWN
